idem_darwin/conf.py
idem_darwin/version.py
idem_darwin/exec/cmdmod.py
idem_darwin/exec/contracts/cmdmod.py
idem_darwin/exec/darwin/init.py
idem_darwin/exec/darwin/service.py
idem_darwin/exec/darwin/status.py
idem_darwin/exec/darwin/contracts/service.py
idem_darwin/grains/darwin/defaults.py
idem_darwin/grains/darwin/init.py
idem_darwin/grains/darwin/hw/cpu.py
idem_darwin/grains/darwin/hw/mem.py
idem_darwin/grains/darwin/hw/platform.py
idem_darwin/grains/darwin/hw/sysctl.py
idem_darwin/grains/darwin/hw/disk/filevault.py
idem_darwin/grains/darwin/hw/disk/ssd.py
idem_darwin/grains/darwin/hw/gpu/pcictl.py
idem_darwin/grains/darwin/net/dns.py
idem_darwin/grains/darwin/net/fqdns.py
idem_darwin/grains/darwin/net/gateway.py
idem_darwin/grains/darwin/net/interfaces.py
idem_darwin/grains/darwin/net/realm.py
idem_darwin/grains/darwin/os/arch.py
idem_darwin/grains/darwin/os/computer.py
idem_darwin/grains/darwin/os/sw_vers.py
idem_darwin/states/cmdmod.py
idem_darwin/states/contracts/cmdmod.py
idem_darwin-8.2.dist-info/METADATA
idem_darwin-8.2.dist-info/WHEEL
idem_darwin-8.2.dist-info/entry_points.txt
idem_darwin-8.2.dist-info/top_level.txt
idem_darwin-8.2.dist-info/RECORD
